codePost_api/__init__.py
codePost_api/errors.py
codePost_api/helpers.py
codePost_api/upload.py
codePost_api/util.py
codePost_api-1.0.13.dist-info/LICENSE
codePost_api-1.0.13.dist-info/METADATA
codePost_api-1.0.13.dist-info/WHEEL
codePost_api-1.0.13.dist-info/top_level.txt
codePost_api-1.0.13.dist-info/RECORD
