Metadata-Version: 2.1
Name: codePost-api
Version: 1.0.13
Summary: Python bindings for the codePost API
Home-page: https://github.com/codepost-io/codePost-api-python
Author: codePost
Author-email: team@codepost.io
License: MIT
Platform: UNKNOWN
Classifier: License :: OSI Approved :: MIT License
Classifier: Programming Language :: Python :: 3
Classifier: Programming Language :: Python :: 3.7
Requires-Dist: requests
Requires-Dist: PyYAML
